{
"meta":{"test_sets":[],"test_metrics":[],"learn_metrics":[{"best_value":"Min","name":"Logloss"}],"launch_mode":"Train","parameters":"","iteration_count":236,"learn_sets":["learn"],"name":"experiment"},
"iterations":[
{"learn":[0.3610271092],"iteration":0,"passed_time":18.74240199,"remaining_time":4404.464467},
{"learn":[0.2861630955],"iteration":1,"passed_time":31.78149307,"remaining_time":3718.434689},
{"learn":[0.2659678849],"iteration":2,"passed_time":46.73719752,"remaining_time":3629.92234},
{"learn":[0.2576617138],"iteration":3,"passed_time":60.81524584,"remaining_time":3527.284258},
{"learn":[0.2536539338],"iteration":4,"passed_time":77.44347615,"remaining_time":3577.888598},
{"learn":[0.2513870981],"iteration":5,"passed_time":97.39500744,"remaining_time":3733.475285},
{"learn":[0.2500257259],"iteration":6,"passed_time":107.965571,"remaining_time":3532.016536},
{"learn":[0.2488724029],"iteration":7,"passed_time":115.9449127,"remaining_time":3304.430011},
{"learn":[0.2481623844],"iteration":8,"passed_time":132.1163651,"remaining_time":3332.26832},
{"learn":[0.2474726655],"iteration":9,"passed_time":146.0345577,"remaining_time":3300.381004},
{"learn":[0.2468464877],"iteration":10,"passed_time":158.388946,"remaining_time":3239.773896},
{"learn":[0.2463041215],"iteration":11,"passed_time":165.7375119,"remaining_time":3093.76689},
{"learn":[0.2458937527],"iteration":12,"passed_time":179.2527891,"remaining_time":3074.874767},
{"learn":[0.2453682115],"iteration":13,"passed_time":187.0140528,"remaining_time":2965.508551},
{"learn":[0.2451129365],"iteration":14,"passed_time":193.355632,"remaining_time":2848.772979},
{"learn":[0.2448180378],"iteration":15,"passed_time":216.3593637,"remaining_time":2974.941252},
{"learn":[0.2445292899],"iteration":16,"passed_time":223.3251426,"remaining_time":2876.953307},
{"learn":[0.2442637178],"iteration":17,"passed_time":231.1823791,"remaining_time":2799.87548},
{"learn":[0.2440342942],"iteration":18,"passed_time":243.9987246,"remaining_time":2786.722276},
{"learn":[0.2438709381],"iteration":19,"passed_time":263.2614773,"remaining_time":2843.223955},
{"learn":[0.2436474922],"iteration":20,"passed_time":269.670978,"remaining_time":2760.917156},
{"learn":[0.2435025566],"iteration":21,"passed_time":276.7381256,"remaining_time":2691.907222},
{"learn":[0.2432658485],"iteration":22,"passed_time":283.1010464,"remaining_time":2621.761865},
{"learn":[0.2430059517],"iteration":23,"passed_time":288.8612663,"remaining_time":2551.607852},
{"learn":[0.2428245039],"iteration":24,"passed_time":294.8077711,"remaining_time":2488.177588},
{"learn":[0.2424456783],"iteration":25,"passed_time":300.5636367,"remaining_time":2427.629373},
{"learn":[0.2421514931],"iteration":26,"passed_time":306.5604328,"remaining_time":2373.004832},
{"learn":[0.2419305831],"iteration":27,"passed_time":334.3000725,"remaining_time":2483.371967},
{"learn":[0.2418054316],"iteration":28,"passed_time":353.4796287,"remaining_time":2523.113212},
{"learn":[0.24152122],"iteration":29,"passed_time":367.2627198,"remaining_time":2521.870676},
{"learn":[0.2413646239],"iteration":30,"passed_time":380.2182297,"remaining_time":2514.346358},
{"learn":[0.2410216042],"iteration":31,"passed_time":388.0501959,"remaining_time":2473.819999},
{"learn":[0.2408330873],"iteration":32,"passed_time":395.4349249,"remaining_time":2432.523932},
{"learn":[0.240622273],"iteration":33,"passed_time":402.643447,"remaining_time":2392.175773},
{"learn":[0.240443904],"iteration":34,"passed_time":410.0682132,"remaining_time":2354.963167},
{"learn":[0.2402793527],"iteration":35,"passed_time":418.1741716,"remaining_time":2323.189842},
{"learn":[0.2401992898],"iteration":36,"passed_time":426.6748931,"remaining_time":2294.819019},
{"learn":[0.2401676881],"iteration":37,"passed_time":431.8345057,"remaining_time":2250.085056},
{"learn":[0.2400059648],"iteration":38,"passed_time":440.9041137,"remaining_time":2227.131036},
{"learn":[0.2398648735],"iteration":39,"passed_time":447.5426723,"remaining_time":2192.959094},
{"learn":[0.2396913393],"iteration":40,"passed_time":453.7958955,"remaining_time":2158.297552},
{"learn":[0.239543807],"iteration":41,"passed_time":461.2340261,"remaining_time":2130.46193},
{"learn":[0.2393626138],"iteration":42,"passed_time":468.5532722,"remaining_time":2103.041431},
{"learn":[0.2390430244],"iteration":43,"passed_time":474.6251825,"remaining_time":2071.091706},
{"learn":[0.2389549883],"iteration":44,"passed_time":479.1125362,"remaining_time":2033.566543},
{"learn":[0.2387948647],"iteration":45,"passed_time":486.6756812,"remaining_time":2010.182161},
{"learn":[0.238650773],"iteration":46,"passed_time":500.511806,"remaining_time":2012.696411},
{"learn":[0.2385719092],"iteration":47,"passed_time":508.0191882,"remaining_time":1989.74182},
{"learn":[0.2385341133],"iteration":48,"passed_time":516.0023732,"remaining_time":1969.233547},
{"learn":[0.2383850185],"iteration":49,"passed_time":527.2883486,"remaining_time":1961.512657},
{"learn":[0.2383246516],"iteration":50,"passed_time":537.8264213,"remaining_time":1950.938979},
{"learn":[0.238196091],"iteration":51,"passed_time":545.0521994,"remaining_time":1928.646244},
{"learn":[0.2380470873],"iteration":52,"passed_time":552.6111435,"remaining_time":1908.072439},
{"learn":[0.2379887602],"iteration":53,"passed_time":562.5603688,"remaining_time":1896.036799},
{"learn":[0.2378237955],"iteration":54,"passed_time":569.9911629,"remaining_time":1875.7891},
{"learn":[0.2378102292],"iteration":55,"passed_time":577.4047082,"remaining_time":1855.943705},
{"learn":[0.2377581347],"iteration":56,"passed_time":587.2730868,"remaining_time":1844.243553},
{"learn":[0.2376215361],"iteration":57,"passed_time":593.7097679,"remaining_time":1822.074805},
{"learn":[0.2374514869],"iteration":58,"passed_time":599.7576847,"remaining_time":1799.273054},
{"learn":[0.2373577777],"iteration":59,"passed_time":610.8397905,"remaining_time":1791.796719},
{"learn":[0.2371187148],"iteration":60,"passed_time":620.2487703,"remaining_time":1779.40221},
{"learn":[0.2370412616],"iteration":61,"passed_time":627.8692505,"remaining_time":1762.084671},
{"learn":[0.2370188714],"iteration":62,"passed_time":641.1206771,"remaining_time":1760.537732},
{"learn":[0.2369520651],"iteration":63,"passed_time":646.6552411,"remaining_time":1737.88596},
{"learn":[0.2367869474],"iteration":64,"passed_time":655.2901171,"remaining_time":1723.917077},
{"learn":[0.2366339572],"iteration":65,"passed_time":664.0858843,"remaining_time":1710.524247},
{"learn":[0.2365882523],"iteration":66,"passed_time":670.6520205,"remaining_time":1691.644649},
{"learn":[0.2364832707],"iteration":67,"passed_time":676.6585861,"remaining_time":1671.744742},
{"learn":[0.2363805945],"iteration":68,"passed_time":682.8539081,"remaining_time":1652.704386},
{"learn":[0.2363639251],"iteration":69,"passed_time":688.8971454,"remaining_time":1633.670373},
{"learn":[0.2362639032],"iteration":70,"passed_time":695.7575272,"remaining_time":1616.901296},
{"learn":[0.2362159683],"iteration":71,"passed_time":701.9101875,"remaining_time":1598.795427},
{"learn":[0.2360491697],"iteration":72,"passed_time":708.8479358,"remaining_time":1582.770048},
{"learn":[0.2360072784],"iteration":73,"passed_time":714.448908,"remaining_time":1564.063826},
{"learn":[0.2359371131],"iteration":74,"passed_time":721.0241949,"remaining_time":1547.798605},
{"learn":[0.235769251],"iteration":75,"passed_time":725.93799,"remaining_time":1528.290505},
{"learn":[0.2357229187],"iteration":76,"passed_time":730.9758757,"remaining_time":1509.417717},
{"learn":[0.2357121243],"iteration":77,"passed_time":735.9750649,"remaining_time":1490.821285},
{"learn":[0.2355353677],"iteration":78,"passed_time":740.5936587,"remaining_time":1471.812714},
{"learn":[0.2354166236],"iteration":79,"passed_time":745.4212759,"remaining_time":1453.571488},
{"learn":[0.2353073982],"iteration":80,"passed_time":753.819768,"remaining_time":1442.494618},
{"learn":[0.2353039227],"iteration":81,"passed_time":759.4386025,"remaining_time":1426.262741},
{"learn":[0.2352561045],"iteration":82,"passed_time":764.6456571,"remaining_time":1409.527537},
{"learn":[0.2352045953],"iteration":83,"passed_time":769.0605746,"remaining_time":1391.633421},
{"learn":[0.2350914551],"iteration":84,"passed_time":774.0361187,"remaining_time":1375.052399},
{"learn":[0.2350852867],"iteration":85,"passed_time":778.5555962,"remaining_time":1357.945807},
{"learn":[0.2350489107],"iteration":86,"passed_time":788.545364,"remaining_time":1350.497233},
{"learn":[0.2350181243],"iteration":87,"passed_time":804.0658933,"remaining_time":1352.292639},
{"learn":[0.2349578908],"iteration":88,"passed_time":813.7125043,"remaining_time":1343.997058},
{"learn":[0.2348506822],"iteration":89,"passed_time":821.4065592,"remaining_time":1332.503974},
{"learn":[0.2348281746],"iteration":90,"passed_time":826.6100384,"remaining_time":1317.125885},
{"learn":[0.2347690609],"iteration":91,"passed_time":833.8399493,"remaining_time":1305.14079},
{"learn":[0.234587602],"iteration":92,"passed_time":840.8685422,"remaining_time":1292.948404},
{"learn":[0.2345302697],"iteration":93,"passed_time":848.8676979,"remaining_time":1282.332054},
{"learn":[0.234463668],"iteration":94,"passed_time":857.7160041,"remaining_time":1273.031122},
{"learn":[0.2344578761],"iteration":95,"passed_time":863.4005683,"remaining_time":1259.125829},
{"learn":[0.2344088106],"iteration":96,"passed_time":868.6459491,"remaining_time":1244.76069},
{"learn":[0.2343243294],"iteration":97,"passed_time":872.8815676,"remaining_time":1229.159759},
{"learn":[0.2342126105],"iteration":98,"passed_time":877.2131011,"remaining_time":1213.92116},
{"learn":[0.2342040824],"iteration":99,"passed_time":880.8458883,"remaining_time":1197.950408},
{"learn":[0.234082505],"iteration":100,"passed_time":885.0505799,"remaining_time":1182.988399},
{"learn":[0.2339943424],"iteration":101,"passed_time":891.2334627,"remaining_time":1170.836118},
{"learn":[0.2339134631],"iteration":102,"passed_time":898.6974288,"remaining_time":1160.453961},
{"learn":[0.2338279402],"iteration":103,"passed_time":903.3733161,"remaining_time":1146.589209},
{"learn":[0.2338227388],"iteration":104,"passed_time":907.923888,"remaining_time":1132.743136},
{"learn":[0.2337759317],"iteration":105,"passed_time":914.7099056,"remaining_time":1121.814035},
{"learn":[0.2337292552],"iteration":106,"passed_time":919.4989691,"remaining_time":1108.554832},
{"learn":[0.2336691655],"iteration":107,"passed_time":924.2035221,"remaining_time":1095.352323},
{"learn":[0.2335846049],"iteration":108,"passed_time":929.460361,"remaining_time":1082.949228},
{"learn":[0.2335517892],"iteration":109,"passed_time":936.3901007,"remaining_time":1072.592297},
{"learn":[0.2333725152],"iteration":110,"passed_time":942.0786137,"remaining_time":1060.89934},
{"learn":[0.2333218066],"iteration":111,"passed_time":946.41752,"remaining_time":1047.819397},
{"learn":[0.2332465404],"iteration":112,"passed_time":952.8427908,"remaining_time":1037.165162},
{"learn":[0.233151324],"iteration":113,"passed_time":972.521185,"remaining_time":1040.768286},
{"learn":[0.2331326299],"iteration":114,"passed_time":1002.990279,"remaining_time":1055.320206},
{"learn":[0.2330968354],"iteration":115,"passed_time":1029.653054,"remaining_time":1065.158331},
{"learn":[0.2329978928],"iteration":116,"passed_time":1049.253114,"remaining_time":1067.189064},
{"learn":[0.2329527729],"iteration":117,"passed_time":1066.13685,"remaining_time":1066.13685},
{"learn":[0.2328773895],"iteration":118,"passed_time":1084.895759,"remaining_time":1066.662217},
{"learn":[0.2327940552],"iteration":119,"passed_time":1095.045363,"remaining_time":1058.543851},
{"learn":[0.2327448173],"iteration":120,"passed_time":1102.638681,"remaining_time":1047.962382},
{"learn":[0.2326032699],"iteration":121,"passed_time":1110.062963,"remaining_time":1037.271949},
{"learn":[0.23257228],"iteration":122,"passed_time":1118.281731,"remaining_time":1027.364517},
{"learn":[0.2325024055],"iteration":123,"passed_time":1125.174585,"remaining_time":1016.286722},
{"learn":[0.2324032097],"iteration":124,"passed_time":1132.28147,"remaining_time":1005.465945},
{"learn":[0.2323986277],"iteration":125,"passed_time":1143.167145,"remaining_time":998.0030628},
{"learn":[0.2323516836],"iteration":126,"passed_time":1150.882848,"remaining_time":987.7655936},
{"learn":[0.2322986266],"iteration":127,"passed_time":1159.478334,"remaining_time":978.309844},
{"learn":[0.2322082308],"iteration":128,"passed_time":1165.689824,"remaining_time":966.8900087},
{"learn":[0.23211046],"iteration":129,"passed_time":1170.952735,"remaining_time":954.7768458},
{"learn":[0.2320959302],"iteration":130,"passed_time":1177.250673,"remaining_time":943.5978673},
{"learn":[0.2319842112],"iteration":131,"passed_time":1183.051839,"remaining_time":932.1014492},
{"learn":[0.2319769209],"iteration":132,"passed_time":1188.14157,"remaining_time":920.1397117},
{"learn":[0.2318657587],"iteration":133,"passed_time":1194.711714,"remaining_time":909.4074243},
{"learn":[0.2318144723],"iteration":134,"passed_time":1201.521724,"remaining_time":898.9162528},
{"learn":[0.2317920639],"iteration":135,"passed_time":1207.817759,"remaining_time":888.1012934},
{"learn":[0.2317421015],"iteration":136,"passed_time":1214.933308,"remaining_time":877.9445071},
{"learn":[0.2316443217],"iteration":137,"passed_time":1222.421972,"remaining_time":868.0967626},
{"learn":[0.2316416254],"iteration":138,"passed_time":1229.438168,"remaining_time":857.953254},
{"learn":[0.2315394333],"iteration":139,"passed_time":1236.055159,"remaining_time":847.5806805},
{"learn":[0.2315202807],"iteration":140,"passed_time":1240.591416,"remaining_time":835.8594646},
{"learn":[0.2314608839],"iteration":141,"passed_time":1247.032376,"remaining_time":825.5003055},
{"learn":[0.2313599069],"iteration":142,"passed_time":1255.055149,"remaining_time":816.2246776},
{"learn":[0.2313019109],"iteration":143,"passed_time":1265.482116,"remaining_time":808.5024633},
{"learn":[0.2311552047],"iteration":144,"passed_time":1272.021773,"remaining_time":798.3033194},
{"learn":[0.2310239371],"iteration":145,"passed_time":1278.547154,"remaining_time":788.145506},
{"learn":[0.2309843701],"iteration":146,"passed_time":1285.489761,"remaining_time":778.2897192},
{"learn":[0.2309522996],"iteration":147,"passed_time":1292.146063,"remaining_time":768.3030647},
{"learn":[0.2308455369],"iteration":148,"passed_time":1298.674867,"remaining_time":758.2866676},
{"learn":[0.2308258959],"iteration":149,"passed_time":1306.721371,"remaining_time":749.1869193},
{"learn":[0.2307441709],"iteration":150,"passed_time":1313.183785,"remaining_time":739.2094153},
{"learn":[0.2306583968],"iteration":151,"passed_time":1318.297378,"remaining_time":728.5327613},
{"learn":[0.2305252525],"iteration":152,"passed_time":1323.905268,"remaining_time":718.1969754},
{"learn":[0.2304733226],"iteration":153,"passed_time":1331.075384,"remaining_time":708.7544254},
{"learn":[0.2304093802],"iteration":154,"passed_time":1339.367572,"remaining_time":699.9275699},
{"learn":[0.2303792893],"iteration":155,"passed_time":1346.373604,"remaining_time":690.4480018},
{"learn":[0.230256267],"iteration":156,"passed_time":1352.500501,"remaining_time":680.557577},
{"learn":[0.2302119583],"iteration":157,"passed_time":1360.028023,"remaining_time":671.4062391},
{"learn":[0.2301412966],"iteration":158,"passed_time":1367.462954,"remaining_time":662.2304872},
{"learn":[0.2301103209],"iteration":159,"passed_time":1376.104522,"remaining_time":653.6496481},
{"learn":[0.2300798785],"iteration":160,"passed_time":1383.356664,"remaining_time":644.4208063},
{"learn":[0.2300325016],"iteration":161,"passed_time":1388.522413,"remaining_time":634.2633244},
{"learn":[0.2300273096],"iteration":162,"passed_time":1393.824863,"remaining_time":624.2283128},
{"learn":[0.2299793567],"iteration":163,"passed_time":1400.465602,"remaining_time":614.8385568},
{"learn":[0.2299262475],"iteration":164,"passed_time":1405.646662,"remaining_time":604.8540183},
{"learn":[0.2298896037],"iteration":165,"passed_time":1414.245491,"remaining_time":596.3685807},
{"learn":[0.2298869865],"iteration":166,"passed_time":1419.816124,"remaining_time":586.630614},
{"learn":[0.2298126677],"iteration":167,"passed_time":1425.675808,"remaining_time":577.0592558},
{"learn":[0.2297715025],"iteration":168,"passed_time":1432.522857,"remaining_time":567.9232627},
{"learn":[0.2297675525],"iteration":169,"passed_time":1439.087304,"remaining_time":558.7044828},
{"learn":[0.2297454336],"iteration":170,"passed_time":1448.058224,"remaining_time":550.4314886},
{"learn":[0.2296929225],"iteration":171,"passed_time":1455.914904,"remaining_time":541.7357783},
{"learn":[0.2296708711],"iteration":172,"passed_time":1464.229556,"remaining_time":533.2165435},
{"learn":[0.2296370786],"iteration":173,"passed_time":1471.712978,"remaining_time":524.4034751},
{"learn":[0.229555042],"iteration":174,"passed_time":1478.558705,"remaining_time":515.3833199},
{"learn":[0.2294974255],"iteration":175,"passed_time":1483.687204,"remaining_time":505.8024559},
{"learn":[0.2294898846],"iteration":176,"passed_time":1492.121704,"remaining_time":497.3739014},
{"learn":[0.2294265656],"iteration":177,"passed_time":1498.363143,"remaining_time":488.2306872},
{"learn":[0.2293254205],"iteration":178,"passed_time":1503.745269,"remaining_time":478.8462587},
{"learn":[0.2293151818],"iteration":179,"passed_time":1512.41727,"remaining_time":470.5298173},
{"learn":[0.2292258605],"iteration":180,"passed_time":1522.686005,"remaining_time":462.6946423},
{"learn":[0.229204823],"iteration":181,"passed_time":1527.850519,"remaining_time":453.3182858},
{"learn":[0.2291305266],"iteration":182,"passed_time":1532.883291,"remaining_time":443.9498056},
{"learn":[0.2290900623],"iteration":183,"passed_time":1538.00102,"remaining_time":434.6524622},
{"learn":[0.2290239442],"iteration":184,"passed_time":1543.09738,"remaining_time":425.394413},
{"learn":[0.2289605191],"iteration":185,"passed_time":1549.772802,"remaining_time":416.6055918},
{"learn":[0.2288738252],"iteration":186,"passed_time":1554.941804,"remaining_time":407.4446438},
{"learn":[0.2287563813],"iteration":187,"passed_time":1560.33479,"remaining_time":398.3833506},
{"learn":[0.2287077032],"iteration":188,"passed_time":1566.783936,"remaining_time":389.6235186},
{"learn":[0.2286725594],"iteration":189,"passed_time":1576.916015,"remaining_time":381.7796668},
{"learn":[0.2285807874],"iteration":190,"passed_time":1588.387994,"remaining_time":374.2275379},
{"learn":[0.2285547794],"iteration":191,"passed_time":1594.479019,"remaining_time":365.4014417},
{"learn":[0.2284909576],"iteration":192,"passed_time":1599.136535,"remaining_time":356.2843056},
{"learn":[0.2284527243],"iteration":193,"passed_time":1603.714454,"remaining_time":347.1959127},
{"learn":[0.2284024535],"iteration":194,"passed_time":1609.0269,"remaining_time":338.3082199},
{"learn":[0.2283158997],"iteration":195,"passed_time":1614.395188,"remaining_time":329.4684058},
{"learn":[0.2282366015],"iteration":196,"passed_time":1619.999594,"remaining_time":320.7105794},
{"learn":[0.2281469247],"iteration":197,"passed_time":1624.503278,"remaining_time":311.7733564},
{"learn":[0.2280362137],"iteration":198,"passed_time":1629.391688,"remaining_time":302.9522235},
{"learn":[0.2279698774],"iteration":199,"passed_time":1634.501219,"remaining_time":294.2102193},
{"learn":[0.2279232419],"iteration":200,"passed_time":1640.294898,"remaining_time":285.6234897},
{"learn":[0.2279144711],"iteration":201,"passed_time":1645.06229,"remaining_time":276.8916727},
{"learn":[0.2278797998],"iteration":202,"passed_time":1649.610351,"remaining_time":268.1632591},
{"learn":[0.2278428718],"iteration":203,"passed_time":1654.817825,"remaining_time":259.5792666},
{"learn":[0.2277966959],"iteration":204,"passed_time":1660.427953,"remaining_time":251.0891051},
{"learn":[0.2277626581],"iteration":205,"passed_time":1665.753475,"remaining_time":242.5854575},
{"learn":[0.2276554781],"iteration":206,"passed_time":1671.409476,"remaining_time":234.1588155},
{"learn":[0.2275520301],"iteration":207,"passed_time":1676.426201,"remaining_time":225.6727578},
{"learn":[0.2275190304],"iteration":208,"passed_time":1681.51839,"remaining_time":217.2296485},
{"learn":[0.2274260424],"iteration":209,"passed_time":1685.667432,"remaining_time":208.701682},
{"learn":[0.2273266305],"iteration":210,"passed_time":1691.587193,"remaining_time":200.4250229},
{"learn":[0.2272712653],"iteration":211,"passed_time":1697.716814,"remaining_time":192.1943563},
{"learn":[0.2272483223],"iteration":212,"passed_time":1702.888489,"remaining_time":183.8799776},
{"learn":[0.2271041089],"iteration":213,"passed_time":1708.259441,"remaining_time":175.6154565},
{"learn":[0.2270701438],"iteration":214,"passed_time":1713.919454,"remaining_time":167.4060862},
{"learn":[0.2270680466],"iteration":215,"passed_time":1719.290115,"remaining_time":159.1935292},
{"learn":[0.2270438883],"iteration":216,"passed_time":1723.736832,"remaining_time":150.9262664},
{"learn":[0.2269850367],"iteration":217,"passed_time":1728.305595,"remaining_time":142.7041317},
{"learn":[0.2269269929],"iteration":218,"passed_time":1733.435739,"remaining_time":134.5589387},
{"learn":[0.2268562078],"iteration":219,"passed_time":1738.225462,"remaining_time":126.4163972},
{"learn":[0.2268062027],"iteration":220,"passed_time":1744.7053,"remaining_time":118.4189118},
{"learn":[0.226766682],"iteration":221,"passed_time":1749.099983,"remaining_time":110.3036025},
{"learn":[0.2267079623],"iteration":222,"passed_time":1756.778464,"remaining_time":102.4130943},
{"learn":[0.2266459348],"iteration":223,"passed_time":1762.981784,"remaining_time":94.44545271},
{"learn":[0.2265981932],"iteration":224,"passed_time":1767.94508,"remaining_time":86.43287058},
{"learn":[0.226544252],"iteration":225,"passed_time":1773.454031,"remaining_time":78.47141729},
{"learn":[0.2264388214],"iteration":226,"passed_time":1778.802759,"remaining_time":70.52521951},
{"learn":[0.2264213989],"iteration":227,"passed_time":1783.694876,"remaining_time":62.58578514},
{"learn":[0.2263214692],"iteration":228,"passed_time":1788.156842,"remaining_time":54.65981613},
{"learn":[0.2262960722],"iteration":229,"passed_time":1792.795708,"remaining_time":46.76858368},
{"learn":[0.226197665],"iteration":230,"passed_time":1796.913271,"remaining_time":38.89422664},
{"learn":[0.2259822971],"iteration":231,"passed_time":1802.039613,"remaining_time":31.06964851},
{"learn":[0.2259415608],"iteration":232,"passed_time":1807.211579,"remaining_time":23.26881862},
{"learn":[0.2258931023],"iteration":233,"passed_time":1811.94298,"remaining_time":15.48669214},
{"learn":[0.2258759035],"iteration":234,"passed_time":1816.571085,"remaining_time":7.730089722},
{"learn":[0.2258259076],"iteration":235,"passed_time":1820.754031,"remaining_time":0}
]}